Workbook

Sheet Realistic Ratings
A1: Fighter Name | B1: Profile URL | C1: CHIN | D1: CARDIO | E1: PUNCH SPEED | F1: PUNCH POWER | G1: KICK SPEED | H1: KICK POWER | I1: ACCURACY | J1: WRESTLING | K1: JIU-JITSU
A2: Kyoji Horiguchi | B2: https://www.ea.com/games/ufc/ufc-6/ufc-6-ratings-hub/ufc-6-kyoji-horiguchi | C2: 84 | D2: 93 | E2: 95 | F2: 82 | G2: 91 | H2: 77 | I2: 92 | J2: 80 | K2: 78
A3: Josh Hokit | B3: https://www.ea.com/games/ufc/ufc-6/ufc-6-ratings-hub/ufc-6-josh-hokit | C3: 85 | D3: 79 | E3: 80 | F3: 80 | G3: 64 | H3: 64 | I3: 78 | J3: 92 | K3: 69
A4: Rich Franklin | B4: https://www.ea.com/games/ufc/ufc-6/ufc-6-ratings-hub/ufc-6-rich-franklin | C4: 77 | D4: 86 | E4: 80 | F4: 86 | G4: 74 | H4: 74 | I4: 80 | J4: 80 | K4: 69
A5: Max Holloway | B5: https://www.ea.com/games/ufc/ufc-6/ufc-6-ratings-hub/ufc-6-max-holloway | C5: 100 | D5: 100 | E5: 95 | F5: 81 | G5: 86 | H5: 79 | I5: 95 | J5: 64 | K5: 60
A6: Conor McGregor | B6: https://www.ea.com/games/ufc/ufc-6/ufc-6-ratings-hub/ufc-6-conor-mcgregor | C6: 90 | D6: 69 | E6: 99 | F6: 97 | G6: 93 | H6: 85 | I6: 100 | J6: 70 | K6: 70
A7: Tank Abbott | B7: https://www.ea.com/games/ufc/ufc-6/ufc-6-ratings-hub/ufc-6-tank-abbott | C7: 89 | D7: 67 | E7: 64 | F7: 99 | G7: 55 | H7: 56 | I7: 69 | J7: 80 | K7: 66
A8: Uroš Medić | B8: https://www.ea.com/games/ufc/ufc-6/ufc-6-ratings-hub/ufc-6-uros-medic | C8: 83 | D8: 77 | E8: 86 | F8: 93 | G8: 83 | H8: 80 | I8: 80 | J8: 61 | K8: 63
A9: Kevin Vallejos | B9: https://www.ea.com/games/ufc/ufc-6/ufc-6-ratings-hub/ufc-6-kevin-vallejos | C9: 88 | D9: 80 | E9: 83 | F9: 93 | G9: 67 | H9: 69 | I9: 85 | J9: 63 | K9: 63
A10: Patricio Pitbull | B10: https://www.ea.com/games/ufc/ufc-6/ufc-6-ratings-hub/ufc-6-patricio-pitbull | C10: 90 | D10: 86 | E10: 89 | F10: 80 | G10: 74 | H10: 69 | I10: 80 | J10: 76 | K10: 84
A11: Aiemann Zahabi | B11: https://www.ea.com/games/ufc/ufc-6/ufc-6-ratings-hub/ufc-6-aiemann-zahabi | C11: 83 | D11: 77 | E11: 74 | F11: 77 | G11: 64 | H11: 71 | I11: 77 | J11: 74 | K11: 69
A12: Bogdan Guskov | B12: https://www.ea.com/games/ufc/ufc-6/ufc-6-ratings-hub/ufc-6-bogdan-guskov | C12: 83 | D12: 77 | E12: 77 | F12: 92 | G12: 69 | H12: 64 | I12: 80 | J12: 70 | K12: 63
A13: Gregory Rodrigues | B13: https://www.ea.com/games/ufc/ufc-6/ufc-6-ratings-hub/ufc-6-gregory-rodrigues | C13: 79 | D13: 72 | E13: 74 | F13: 94 | G13: 72 | H13: 78 | I13: 80 | J13: 83 | K13: 78
... A164: Yan Xiaonan | B164: https://www.ea.com/games/ufc/ufc-6/ufc-6-ratings-hub/ufc-6-yan-xiaonan | C164: 80 | D164: 89 | E164: 86 | F164: 83 | G164: 80 | H164: 69 | I164: 77 | J164: 70 | K164: 62

Sheet Anchor Summary
A1: Fighter | B1: Raw CHIN | C1: Final CHIN | D1: Raw CARDIO | E1: Final CARDIO | F1: Raw PUNCH SPEED | G1: Final PUNCH SPEED | H1: Raw PUNCH POWER | I1: Final PUNCH POWER | J1: Raw TAKEDOWNS | K1: Raw GROUND STRIKING | L1: Final WRESTLING | M1: Raw SUBMISSION OFFENSE | N1: Final JIU-JITSU | O1: Narrative Rationale
A2: Max Holloway | B2: 97 | C2: 100 | D2: 100 | E2: 100 | F2: 96 | G2: 95 | H2: 89 | I2: 81 | J2: 86 | K2: 91 | L2: 74 | M2: 91 | N2: 80 | O2: Peak-identity durability/cardio anchor; punch power held at volume-striker floor rather than artificially crushed.
A3: Merab Dvalishvili | B3: 94 | C3: 94 | D3: 100 | E3: 100 | F3: 94 | G3: 86 | H3: 90 | I3: 73 | J3: 100 | K3: 93 | L3: 100 | M3: 93 | N3: 82 | O3: Missing raw TAKEDOWNS imputed to 100 before merge; cardio and wrestling set as historic engine/control anchors.
A4: Derrick Lewis | B4: 93 | C4: 83 | D4: 88 | E4: 57 | F4: 93 | G4: 78 | H4: 100 | I4: 100 | J4: 87 | K4: 100 | L4: 67 | M4: 83 | N4: 58 | O4: One-shot power preserved at 100; cardio and submission-grappling safety nets stripped.
A5: Conor McGregor | B5: 95 | C5: 88 | D5: 88 | E5: 69 | F5: 100 | G5: 100 | H5: 100 | I5: 97 | J5: 84 | K5: 94 | L5: 80 | M5: 84 | N5: 70 | O5: Hand speed and accuracy retained as defining 100s; cardio exposed and wrestling set to eye-test 80.
A6: Alexandre Pantoja | B6: 100 | C6: 92 | D6: 95 | E6: 94 | F6: 95 | G6: 90 | H6: 96 | I6: 88 | J6: 92 | K6: 92 | L6: 90 | M6: 99 | N6: 97 | O6: Raw 100 chin reduced after damage/KO context; elite grappling retained without game-balance inflation.
A7: Cody Garbrandt | B7: 90 | C7: 62 | D7: 93 | E7: 84 | F7: 99 | G7: 100 | H7: 98 | I7: 94 | J7: 90 | K7: 92 | L7: 84 | M7: 86 | N7: 64 | O7: Fast-hands identity protected with 100 punch speed; chin sharply reduced to reflect repeated knockout vulnerability.

Sheet Distribution Audit
A1: Attribute | B1: Mean | C1: Min | D1: Max | E1: Below 60 | F1: 60–69 | G1: 70–79 | H1: 80–89 | I1: 90–99 | J1: Count 100 | K1: 100-Rated Fighters
A2: CHIN | B2: =AVERAGE('Realistic Ratings'!C2:C164) -> 82.993865 | C2: =MIN('Realistic Ratings'!C2:C164) -> 62 | D2: =MAX('Realistic Ratings'!C2:C164) -> 100 | E2: =COUNTIF('Realistic Ratings'!C2:C164,"<60") -> 0 | F2: =COUNTIFS('Realistic Ratings'!C2:C164,">=60",'Realistic Ratings'!C2:C164,"<=69") -> 4 | G2: =COUNTIFS('Realistic Ratings'!C2:C164,">=70",'Realistic Ratings'!C2:C164,"<=79") -> 37 | H2: =COUNTIFS('Realistic Ratings'!C2:C164,">=80",'Realistic Ratings'!C2:C164,"<=89") -> 100 | I2: =COUNTIFS('Realistic Ratings'!C2:C164,">=90",'Realistic Ratings'!C2:C164,"<=99") -> 19 | J2: =COUNTIF('Realistic Ratings'!C2:C164,100) -> 3 | K2: Max Holloway, Dan Hooker
A3: CARDIO | B3: =AVERAGE('Realistic Ratings'!D2:D164) -> 82.809816 | C3: =MIN('Realistic Ratings'!D2:D164) -> 57 | D3: =MAX('Realistic Ratings'!D2:D164) -> 100 | E3: =COUNTIF('Realistic Ratings'!D2:D164,"<60") -> 1 | F3: =COUNTIFS('Realistic Ratings'!D2:D164,">=60",'Realistic Ratings'!D2:D164,"<=69") -> 10 | G3: =COUNTIFS('Realistic Ratings'!D2:D164,">=70",'Realistic Ratings'!D2:D164,"<=79") -> 46 | H3: =COUNTIFS('Realistic Ratings'!D2:D164,">=80",'Realistic Ratings'!D2:D164,"<=89") -> 71 | I3: =COUNTIFS('Realistic Ratings'!D2:D164,">=90",'Realistic Ratings'!D2:D164,"<=99") -> 33 | J3: =COUNTIF('Realistic Ratings'!D2:D164,100) -> 2 | K3: Max Holloway, Merab Dvalishvili
A4: PUNCH SPEED | B4: =AVERAGE('Realistic Ratings'!E2:E164) -> 82.325153 | C4: =MIN('Realistic Ratings'!E2:E164) -> 63 | D4: =MAX('Realistic Ratings'!E2:E164) -> 100 | E4: =COUNTIF('Realistic Ratings'!E2:E164,"<60") -> 0 | F4: =COUNTIFS('Realistic Ratings'!E2:E164,">=60",'Realistic Ratings'!E2:E164,"<=69") -> 7 | G4: =COUNTIFS('Realistic Ratings'!E2:E164,">=70",'Realistic Ratings'!E2:E164,"<=79") -> 50 | H4: =COUNTIFS('Realistic Ratings'!E2:E164,">=80",'Realistic Ratings'!E2:E164,"<=89") -> 76 | I4: =COUNTIFS('Realistic Ratings'!E2:E164,">=90",'Realistic Ratings'!E2:E164,"<=99") -> 28 | J4: =COUNTIF('Realistic Ratings'!E2:E164,100) -> 2 | K4: Conor McGregor, Cody Garbrandt
A5: PUNCH POWER | B5: =AVERAGE('Realistic Ratings'!F2:F164) -> 81.601227 | C5: =MIN('Realistic Ratings'!F2:F164) -> 61 | D5: =MAX('Realistic Ratings'!F2:F164) -> 100 | E5: =COUNTIF('Realistic Ratings'!F2:F164,"<60") -> 0 | F5: =COUNTIFS('Realistic Ratings'!F2:F164,">=60",'Realistic Ratings'!F2:F164,"<=69") -> 8 | G5: =COUNTIFS('Realistic Ratings'!F2:F164,">=70",'Realistic Ratings'!F2:F164,"<=79") -> 56 | H5: =COUNTIFS('Realistic Ratings'!F2:F164,">=80",'Realistic Ratings'!F2:F164,"<=89") -> 77 | I5: =COUNTIFS('Realistic Ratings'!F2:F164,">=90",'Realistic Ratings'!F2:F164,"<=99") -> 21 | J5: =COUNTIF('Realistic Ratings'!F2:F164,100) -> 1 | K5: Alex Pereira, Derrick Lewis
A6: KICK SPEED | B6: =AVERAGE('Realistic Ratings'!G2:G164) -> 78.877301 | C6: =MIN('Realistic Ratings'!G2:G164) -> 55 | D6: =MAX('Realistic Ratings'!G2:G164) -> 100 | E6: =COUNTIF('Realistic Ratings'!G2:G164,"<60") -> 3 | F6: =COUNTIFS('Realistic Ratings'!G2:G164,">=60",'Realistic Ratings'!G2:G164,"<=69") -> 26 | G6: =COUNTIFS('Realistic Ratings'!G2:G164,">=70",'Realistic Ratings'!G2:G164,"<=79") -> 52 | H6: =COUNTIFS('Realistic Ratings'!G2:G164,">=80",'Realistic Ratings'!G2:G164,"<=89") -> 60 | I6: =COUNTIFS('Realistic Ratings'!G2:G164,">=90",'Realistic Ratings'!G2:G164,"<=99") -> 20 | J6: =COUNTIF('Realistic Ratings'!G2:G164,100) -> 2 | K6: Israel Adesanya, Stephen Thompson
A7: KICK POWER | B7: =AVERAGE('Realistic Ratings'!H2:H164) -> 77.257669 | C7: =MIN('Realistic Ratings'!H2:H164) -> 56 | D7: =MAX('Realistic Ratings'!H2:H164) -> 100 | E7: =COUNTIF('Realistic Ratings'!H2:H164,"<60") -> 2 | F7: =COUNTIFS('Realistic Ratings'!H2:H164,">=60",'Realistic Ratings'!H2:H164,"<=69") -> 35 | G7: =COUNTIFS('Realistic Ratings'!H2:H164,">=70",'Realistic Ratings'!H2:H164,"<=79") -> 58 | H7: =COUNTIFS('Realistic Ratings'!H2:H164,">=80",'Realistic Ratings'!H2:H164,"<=89") -> 56 | I7: =COUNTIFS('Realistic Ratings'!H2:H164,">=90",'Realistic Ratings'!H2:H164,"<=99") -> 10 | J7: =COUNTIF('Realistic Ratings'!H2:H164,100) -> 2 | K7: Alex Pereira, Edson Barboza
A8: ACCURACY | B8: =AVERAGE('Realistic Ratings'!I2:I164) -> 80.128834 | C8: =MIN('Realistic Ratings'!I2:I164) -> 63 | D8: =MAX('Realistic Ratings'!I2:I164) -> 100 | E8: =COUNTIF('Realistic Ratings'!I2:I164,"<60") -> 0 | F8: =COUNTIFS('Realistic Ratings'!I2:I164,">=60",'Realistic Ratings'!I2:I164,"<=69") -> 21 | G8: =COUNTIFS('Realistic Ratings'!I2:I164,">=70",'Realistic Ratings'!I2:I164,"<=79") -> 53 | H8: =COUNTIFS('Realistic Ratings'!I2:I164,">=80",'Realistic Ratings'!I2:I164,"<=89") -> 65 | I8: =COUNTIFS('Realistic Ratings'!I2:I164,">=90",'Realistic Ratings'!I2:I164,"<=99") -> 22 | J8: =COUNTIF('Realistic Ratings'!I2:I164,100) -> 2 | K8: Conor McGregor, Sean O'Malley
A9: WRESTLING | B9: =AVERAGE('Realistic Ratings'!J2:J164) -> 77.834356 | C9: =MIN('Realistic Ratings'!J2:J164) -> 60 | D9: =MAX('Realistic Ratings'!J2:J164) -> 100 | E9: =COUNTIF('Realistic Ratings'!J2:J164,"<60") -> 0 | F9: =COUNTIFS('Realistic Ratings'!J2:J164,">=60",'Realistic Ratings'!J2:J164,"<=69") -> 26 | G9: =COUNTIFS('Realistic Ratings'!J2:J164,">=70",'Realistic Ratings'!J2:J164,"<=79") -> 72 | H9: =COUNTIFS('Realistic Ratings'!J2:J164,">=80",'Realistic Ratings'!J2:J164,"<=89") -> 47 | I9: =COUNTIFS('Realistic Ratings'!J2:J164,">=90",'Realistic Ratings'!J2:J164,"<=99") -> 13 | J9: =COUNTIF('Realistic Ratings'!J2:J164,100) -> 5 | K9: Merab Dvalishvili, Khabib Nurmagomedov, Georges St Pierre
A10: JIU-JITSU | B10: =AVERAGE('Realistic Ratings'!K2:K164) -> 76.472393 | C10: =MIN('Realistic Ratings'!K2:K164) -> 57 | D10: =MAX('Realistic Ratings'!K2:K164) -> 100 | E10: =COUNTIF('Realistic Ratings'!K2:K164,"<60") -> 3 | F10: =COUNTIFS('Realistic Ratings'!K2:K164,">=60",'Realistic Ratings'!K2:K164,"<=69") -> 41 | G10: =COUNTIFS('Realistic Ratings'!K2:K164,">=70",'Realistic Ratings'!K2:K164,"<=79") -> 59 | H10: =COUNTIFS('Realistic Ratings'!K2:K164,">=80",'Realistic Ratings'!K2:K164,"<=89") -> 44 | I10: =COUNTIFS('Realistic Ratings'!K2:K164,">=90",'Realistic Ratings'!K2:K164,"<=99") -> 14 | J10: =COUNTIF('Realistic Ratings'!K2:K164,100) -> 2 | K10: Charles Oliveira, Mackenzie Dern
A13: Global Mean (all 9 stats) | B13: =AVERAGE('Realistic Ratings'!C2:K164) -> 80.033401

Sheet Methodology
A1: UFC 6 Realistic Ratings Re-Architecture
A2: Scope | B2: 163 fighter rows retained. Fighter Name and Profile URL preserved exactly from retained source rows.
A3: Cleaning | B3: Removed 3 non-fighter news/article rows: UFC 6 New Rostered Fighters - June 5, 2026; EA SPORTS UFC 6: Introducing Flow States; EA SPORTS™ UFC® 6 Ratings: An Evolution.
A4: Missing value imputation | B4: Merab Dvalishvili TAKEDOWNS was blank; imputed to raw 100 as an elite baseline before any merge/scaling.
A5: Rating identity | B5: Ratings represent each fighter's recognizable career/competitive peak identity, not a strict age-adjusted August 2026 current-form snapshot.
A6: Nonlinear scale | B6: Base formula: Rating = ROUND(55 + 45 × ((CLIP(raw,80,100)-80)/20)^1.70). Non-anchor raw 100s are capped at 99 until historical 100 anchors are explicitly awarded.
A7: Curve examples | B7: Raw 90→69, 91→71, 94→80, 97→89, 99→96, 100→100. This makes the top-end increments progressively more valuable.
A8: WRESTLING merge | B8: Pre-scale composite = 62% TAKEDOWNS + 38% GROUND STRIKING. Narrative overrides then account for sprawl/anti-wrestling, opponent quality, control, and defensive wrestling.
A9: JIU-JITSU merge | B9: Pre-scale composite = 80% SUBMISSION OFFENSE + 20% defensive grappling proxy; proxy = 55% GROUND STRIKING + 45% TAKEDOWNS. Narrative overrides address guard retention/submission survival.
A10: Narrative overlay | B10: High-confidence contextual overlays were applied to 83 roster entries for identity-defining strengths, known specialist weaknesses, durability, cardio, and grappling/striking archetypes. Other cells retain the nonlinear source transformation.
A11: Volume punch-power floor | B11: Max Holloway set to 81 and Cory Sandhagen held at 82 so elite volume striking remains damaging without pretending they are one-shot power punchers.
A12: Wrestling eye-test anchors | B12: Conor McGregor WRESTLING = 80; Max Holloway WRESTLING = 74, deliberately separating sprawl/hip mechanics and elite-wrestler opposition from raw takedown-defense percentages.
A13: CHIN calibration | B13: Max Holloway CHIN = 100 as a peak durability identity anchor; Alexandre Pantoja raw CHIN 100 reduced to 92 after damage/KO context; Cody Garbrandt reduced to 62 to expose repeated KO vulnerability.
... A22: Khabib Nurmagomedov vs Conor McGregor | B22: https://ufcstats.com/fight-details/3eea92e7f26fb05b
